fluidspy/__init__.py
fluidspy/animate/__init__.py
fluidspy/animate/animation.py
fluidspy/numerical/__init__.py
fluidspy/numerical/constant.py
fluidspy/numerical/state.py
fluidspy/numerical/step.py
fluidspy/numerical/boundary/__init__.py
fluidspy/numerical/boundary/composite.py
fluidspy/numerical/boundary/conditions.py
fluidspy/numerical/boundary/direction.py
fluidspy/numerical/dim/__init__.py
fluidspy/numerical/dim/dimension.py
fluidspy/numerical/material_properties/__init__.py
fluidspy/numerical/material_properties/material.py
fluidspy/numerical/methods/__init__.py
fluidspy/numerical/methods/early_stopping.py
fluidspy/numerical/methods/finite_differential.py
fluidspy/numerical/methods/fdm/__init__.py
fluidspy/numerical/methods/fdm/ftcs.py
fluidspy/standard/__init__.py
fluidspy/standard/one_dim_constant.py
fluidspy/tests/__init__.py
fluidspy/tests/test_animation.py
fluidspy/tests/test_boundary.py
fluidspy/tests/test_dims.py
fluidspy/tests/test_fdm.py
fluidspy/tests/test_material.py
fluidspy-1.0.1.dist-info/LICENSE.txt
fluidspy-1.0.1.dist-info/METADATA
fluidspy-1.0.1.dist-info/WHEEL
fluidspy-1.0.1.dist-info/top_level.txt
fluidspy-1.0.1.dist-info/RECORD
