Metadata-Version: 2.1
Name: fluidspy
Version: 1.0.1
Summary: Implementation of CFD methods in Python
Home-page: https://github.com/AVAniketh0905/fluidspy.git
Author: A V Aniketh
Author-email: adimoolamaniketh@gmail.com
License: MIT
Classifier: Programming Language :: Python :: 3
Classifier: Operating System :: OS Independent
Requires-Python: >=3.10
License-File: LICENSE.txt
Requires-Dist: numpy >=1.24.0
Requires-Dist: typing >=3.7
Requires-Dist: scipy >=1.11.4
Requires-Dist: matplotlib >=3.8.2
Provides-Extra: dev
Requires-Dist: twine >=4.0.0 ; extra == 'dev'
Requires-Dist: pytest ; extra == 'dev'
Requires-Dist: ruff ; extra == 'dev'
Requires-Dist: black ; extra == 'dev'
